{"name": "Crypto Legends 2/20 - AS", "description": "In this 2020 series, we will immortalize the 20 most renegade characters in Crypto. Each profile will have 10 copies. Collect all 20 Crypto Legends, and you will achieve a mythical glory and get a redeemable special price from the creator! About Ameen: The sex workers own noble knight who first discovered Bitcoin while ordering magic mushrooms on Silkroad back in the day, has made a place in our Crypto Legends Hall of fame. Ameen is famous for his worshipping the Meditations on Moloch, an essay by web philosopher Scott Alexander. Moloch has moved Ameen to the darker, yet more honest place of Ethereum many undiscovered paths. He's currently CEO of Spankchain, Summoner of MolochDAO, Blood Mage & a True Degenerate at several different secret sex clubs around the world.", "collection_name": "Rarible", "collection_description": "Create and sell digital collectibles secured with blockchain technology. Rarible is home to thousands of artists and collectors, creating and exchanging immutable art without using code. Trade with RARI token on OpenSea.", "eth_price": "250000000000000000", "eth_price_decimal": 18, "usd_price": 591.8433792999999, "usd_volume": 10720480962.0, "usd_marketcap": 67315962016.0, "transaction_time": "2020-12-07T13:40:14", "media_filenames": ["data/preprocessed/media/tmp/6579.gif"], "has_audio_in_video": false}