{"name": "The Little Mermaid's Dream", "description": "Original C.K. fine art aquarelle on paper goes blockchain. Limited edition (only 8 available).", "collection_name": "Rarible", "collection_description": "Create and sell digital collectibles secured with blockchain technology. Rarible is home to thousands of artists and collectors, creating and exchanging immutable art without using code. Trade with RARI token on OpenSea.", "eth_price": "560000000000000000", "eth_price_decimal": 18, "usd_price": 341.808669, "usd_volume": 11929918060.0, "usd_marketcap": 38592810957.0, "transaction_time": "2020-10-07T03:48:40", "media_filenames": ["data/preprocessed/media/tmp/6714.jpg"], "has_audio_in_video": false}