{"name": "www.tsowf.tumblr.com | Song A Day #368", "description": "\"The story of wandering fall I know you might not get it at all But it may help if you go to t s o w f I made a little page for it Where I explained it a bit So when you see scene 3 act 3 you're not confused though it may make no sense to you And the songs are too short and you want to say boo just bear with me it's an experiment cause i'll be without internet for the next ten days i'll be out of the country yeah on in a trip into the wilderness t s o w f check it out and let me know what you think it's snow out side and i've gotta catch a flight i'll see you on the 14th or so love jonathann\"", "collection_name": "Song A Day", "collection_description": "### Hello! I'm Jonathan Mann! I've been writing, producing and sharing a Song A Day for 12 years. Now I'm making each one available as a unique NFT for the first time. Inspired by CryptoPunks, I've cataloged each Song A Day's attributes. Read more about [this](https://www.notion.so/Song-A-Day-NFT-eca353975b5e4ae6aaca375c1). **Some highlights from Song A Day:** - I hold the Guinness World Record For Most Consecutive Days Writing A Song. - I performed live on stage with Vitalik Buterin at DevCon. - I performed [live](https://www.youtube.com/watch?v=aW3e2vZT6Ys) on the Rachel Maddow show. - Steve Jobs used a [song](https://www.youtube.com/watch?v=xFyXoPi9FNs&t=8s) of mine to open an Apple press conference - Steve Wozniak's wife hired me to write the Woz a birthday song (twice). - [This song](https://twitter.com/songadaymann/status/1310706301643755526?s=20) was featured in the James Comey mini-series \"Fuck You, James Comey\". - My song Baby Yoda, Baby Baby Yoda went via TikTok.", "eth_price": "120000000000000000", "eth_price_decimal": 18, "usd_price": 3227.0, "usd_volume": 13296586731.0, "usd_marketcap": 378558550046.0, "transaction_time": "2021-08-29T03:42:47", "media_filenames": ["data/preprocessed/media/tmp/7078.mp4"], "has_audio_in_video": true}