{"name": "King Bull", "description": "Art that was made but never released for a Vaporwave Album. Album in question was called 'If You Live The Life, Can We Die The Death?' by GrounBEEFtaxi. Album was pretty rad but was put out before any conceptual art could be added.", "collection_name": "SuperRare", "collection_description": "SuperRare makes it easy to create, sell, and collect rare digital art. SuperRare's smart contract platform allows artists to release limited-edition digital artwork tracked on the blockchain, making the pieces rare, verified, and collectible. Filter the crypto art world's best selling works by artist name, creation type, and year of birth on OpenSea.", "eth_price": "250000000000000000", "eth_price_decimal": 18, "usd_price": 112.34712379999999, "usd_volume": 22134741655.0, "usd_marketcap": 12366138225.0, "transaction_time": "2020-03-12T06:13:16", "media_filenames": ["data/preprocessed/media/8339.jpg"], "has_audio_in_video": false}