{"name": "Gradually, Then Suddenly.", "description": "It starts as a tiny trickle, which goes on for years or decades, unnoticed. This trickle turns into a stream and some people start to see the signs, though they are usually dismissed. Meanwhile, evidence builds. Then comes a flash point. Some event, or combination of events, provides the catalyst for the stream (which is by now more a river) to break the banks and all of the sudden everyone is in 10 feet deep. Are you prepared?", "collection_name": "SuperRare", "collection_description": "SuperRare makes it easy to create, sell, and collect rare digital art. SuperRare's smart contract platform allows artists to release limited-edition digital artwork tracked on the blockchain, making the pieces rare, verified, and collectible. Filter the crypto art world's best selling works by artist name, creation type, and year of birth on OpenSea.", "eth_price": "190000000000000000", "eth_price_decimal": 18, "usd_price": 1911.18, "usd_volume": 15688092552.0, "usd_marketcap": 223049018143.0, "transaction_time": "2021-07-15T22:33:24", "media_filenames": ["data/preprocessed/media/8475.gif"], "has_audio_in_video": false}